{
  "effective_date": "2025-10-01",
  "half_rate_keywords": [
    "INX",
    "NASDAQ100"
  ],
  "maker_rate": 0.0175,
  "maker_series": [
    "CLAIMS",
    "CPI",
    "TENY",
    "TNEY",
    "WEATHER"
  ],
  "series_half_rate": [
    "INX",
    "INXU",
    "NASDAQ100",
    "NASDAQ100U",
    "SP500",
    "SPX"
  ],
  "series_overrides": [
    {
      "maker_rate": 0.0,
      "series": "INX",
      "taker_rate": 0.035
    },
    {
      "maker_rate": 0.0,
      "series": "INXU",
      "taker_rate": 0.035
    },
    {
      "maker_rate": 0.0,
      "series": "NASDAQ100",
      "taker_rate": 0.035
    },
    {
      "maker_rate": 0.0,
      "series": "NASDAQ100U",
      "taker_rate": 0.035
    }
  ],
  "taker_rate": 0.07
}